{
  "./dist/react-big-calendar.js": {
    "bundled": 525449,
    "minified": 164408,
    "gzipped": 51632
  },
  "./dist/react-big-calendar.min.js": {
    "bundled": 430017,
    "minified": 132577,
    "gzipped": 42425
  },
  "dist/react-big-calendar.esm.js": {
    "bundled": 185554,
    "minified": 87500,
    "gzipped": 21669,
    "treeshaked": {
      "rollup": {
        "code": 62542,
        "import_statements": 1590
      },
      "webpack": {
        "code": 67195
      }
    }
  },
  "./dist/react-big-calendar.esm.js": {
    "bundled": 455232,
    "minified": 142513,
    "gzipped": 45926
  }
}
